downloader/__init__.py
downloader/downloader.py
downloader/utils.py
multithreaded_downloader-1.5.dist-info/METADATA
multithreaded_downloader-1.5.dist-info/WHEEL
multithreaded_downloader-1.5.dist-info/entry_points.txt
multithreaded_downloader-1.5.dist-info/top_level.txt
multithreaded_downloader-1.5.dist-info/RECORD
